fractpy/__init__.py
fractpy/function.py
fractpy/zoom.py
fractpy/models/__init__.py
fractpy/models/newton.py
fractpy-0.0.4.dist-info/LICENSE
fractpy-0.0.4.dist-info/WHEEL
fractpy-0.0.4.dist-info/METADATA
fractpy-0.0.4.dist-info/RECORD
