Metadata-Version: 2.1
Name: fractpy
Version: 0.0.4
Summary: A library to generate fractals
Home-page: https://github.com/asinghgaba/fractpy
Author: Amarjit Singh Gaba
Author-email: asinghgaba@gmail.com
Requires-Python: >=3.6
Classifier: License :: OSI Approved :: MIT License
Classifier: Operating System :: OS Independent
Classifier: Programming Language :: Python :: 3
Requires-Dist: numpy >=1.18.0
Requires-Dist: sympy >=1.5
Requires-Dist: matplotlib >=3.1.0
Requires-Dist: sphinx ; extra == "doc"
Requires-Dist: sphinx-rtd-theme ; extra == "doc"
Provides-Extra: doc
